MusicBGX/__init__.py
MusicBGX-1.0.7.dist-info/LICENSE
MusicBGX-1.0.7.dist-info/METADATA
MusicBGX-1.0.7.dist-info/WHEEL
MusicBGX-1.0.7.dist-info/top_level.txt
MusicBGX-1.0.7.dist-info/RECORD
